odoo/addons/budget_control_operating_unit/README.rst
odoo/addons/budget_control_operating_unit/__init__.py
odoo/addons/budget_control_operating_unit/__manifest__.py
odoo/addons/budget_control_operating_unit/hooks.py
odoo/addons/budget_control_operating_unit/models/__init__.py
odoo/addons/budget_control_operating_unit/models/base_budget_move.py
odoo/addons/budget_control_operating_unit/models/budget_control.py
odoo/addons/budget_control_operating_unit/models/budget_move_adjustment.py
odoo/addons/budget_control_operating_unit/models/budget_transfer.py
odoo/addons/budget_control_operating_unit/models/budget_transfer_item.py
odoo/addons/budget_control_operating_unit/readme/CONTRIBUTORS.md
odoo/addons/budget_control_operating_unit/readme/DESCRIPTION.md
odoo/addons/budget_control_operating_unit/readme/USAGE.md
odoo/addons/budget_control_operating_unit/report/__init__.py
odoo/addons/budget_control_operating_unit/report/budget_monitor_report.py
odoo/addons/budget_control_operating_unit/report/budget_monitor_report_view.xml
odoo/addons/budget_control_operating_unit/security/budget_control_security.xml
odoo/addons/budget_control_operating_unit/static/description/icon.png
odoo/addons/budget_control_operating_unit/static/description/index.html
odoo/addons/budget_control_operating_unit/tests/__init__.py
odoo/addons/budget_control_operating_unit/tests/test_budget_control_operating_unit.py
odoo/addons/budget_control_operating_unit/views/budget_control_view.xml
odoo/addons/budget_control_operating_unit/views/budget_move_adjustment_view.xml
odoo/addons/budget_control_operating_unit/views/budget_transfer_item_view.xml
odoo/addons/budget_control_operating_unit/views/budget_transfer_view.xml
odoo_addon_budget_control_operating_unit-18.0.1.0.1.dist-info/METADATA
odoo_addon_budget_control_operating_unit-18.0.1.0.1.dist-info/WHEEL
odoo_addon_budget_control_operating_unit-18.0.1.0.1.dist-info/top_level.txt
odoo_addon_budget_control_operating_unit-18.0.1.0.1.dist-info/RECORD
